citiesnearby/__init__.py
citiesnearby/main.py
citiesnearby-0.1.4.dist-info/METADATA
citiesnearby-0.1.4.dist-info/WHEEL
citiesnearby-0.1.4.dist-info/top_level.txt
citiesnearby-0.1.4.dist-info/RECORD
