Metadata-Version: 2.1
Name: citiesnearby
Version: 0.1.4
Summary: Library to use CitiesNearby API.
Requires: requests
